peerpyrtc/__init__.py
peerpyrtc/broadcaster.py
peerpyrtc/peerpyrtc.py
peerpyrtc/signaling.py
peerpyrtc-0.2.2.dist-info/METADATA
peerpyrtc-0.2.2.dist-info/WHEEL
peerpyrtc-0.2.2.dist-info/top_level.txt
peerpyrtc-0.2.2.dist-info/RECORD
