Metadata-Version: 2.4
Name: peerpyrtc
Version: 0.2.2
Summary: A Python-based WebRTC signaling and data channel library
Author-email: Sagnik <sagnify2022@gmail.com>
License: MIT
Requires-Python: >=3.10
Requires-Dist: aiortc>=1.5.0
